.DS_Store
woyera/__init__.py
woyera/api.py
woyera-4.0.2.dist-info/LICENSE
woyera-4.0.2.dist-info/METADATA
woyera-4.0.2.dist-info/WHEEL
woyera-4.0.2.dist-info/top_level.txt
woyera-4.0.2.dist-info/RECORD
