Metadata-Version: 2.1
Name: woyera
Version: 4.0.2
Summary: Library for Woyera Data Cleaning API
Home-page: https://github.com/asharma327/woyera_python.git
Author: Woyera Team
Author-email: admin@woyera.com
License: UNKNOWN
Platform: UNKNOWN
Classifier: Programming Language :: Python :: 3
Classifier: License :: OSI Approved :: MIT License
Classifier: Operating System :: OS Independent
Requires-Dist: requests
